mmtpygments/__init__.py
mmtpygments/mmt_lexer.py
mmtpygments/mmt_relational_lexer.py
mmtpygments/mmt_style.py
mmtpygments/test/__init__.py
mmtpygments/test/test.py
mmtpygments-0.2.0.dist-info/LICENSE
mmtpygments-0.2.0.dist-info/METADATA
mmtpygments-0.2.0.dist-info/WHEEL
mmtpygments-0.2.0.dist-info/entry_points.txt
mmtpygments-0.2.0.dist-info/top_level.txt
mmtpygments-0.2.0.dist-info/RECORD
