Metadata-Version: 2.1
Name: mmtpygments
Version: 0.2.0
Summary: Pygments plugin for MMT surface syntax (lexer & style)
Home-page: https://github.com/ComFreek/mmtpygments
Author: ComFreek
Author-email: comfreek@outlook.com
Maintainer: ComFreek
Maintainer-email: comfreek@outlook.com
License: UNKNOWN
Keywords: pygments highlighting mmt minted
Platform: UNKNOWN
Classifier: Development Status :: 4 - Beta
Classifier: Intended Audience :: End Users/Desktop
Classifier: Intended Audience :: Science/Research
Classifier: License :: OSI Approved :: ISC License (ISCL)
Classifier: Operating System :: OS Independent
Classifier: Programming Language :: Python
Classifier: Topic :: Documentation
Classifier: Topic :: Multimedia :: Graphics :: Presentation
Classifier: Programming Language :: Python :: 3.6
Classifier: Programming Language :: Python :: 3.7
Requires-Python: >=3.6
Requires-Dist: pygments
